<?xml version="1.0" encoding="utf-8" ?>

<!--
  French resources for the Reversi.Model assembly.
  
  Author: OrdinaSoft
          Patrick Lanz
          Lausanne
          info@ordinasoft.ch

  First version: March 14, 2021
-->


<Texts>


  <Group Name="BoardTransform">
    <Text Name="LeftBottomHorizontal">Du coin en bas à gauche, avec ligne horizontale</Text>
    <Text Name="LeftBottomVertical">Du coin en bas à gauche, avec ligne verticale</Text>
    <Text Name="LeftTopHorizontal">Du coin en haut à gauche, avec ligne horizontale</Text>
    <Text Name="LeftTopVertical">Du coin en haut à gauche, avec ligne verticale</Text>
    <Text Name="RightBottomHorizontal">Du coin en bas à droite, avec ligne horizontale</Text>
    <Text Name="RightBottomVertical">Du coin en bas à droite, avec ligne verticale</Text>
    <Text Name="RightTopHorizontal">Du coin en haut à droite, avec ligne horizontale</Text>
    <Text Name="RightTopVertical">Du coin en haut à droite, avec ligne verticale</Text>
  </Group>


  <Group Name="StartPosition">
    <Text Name="Empty">Plateau vide</Text>
    <Text Name="LightBottom">Pions blancs en bas</Text>
    <Text Name="LightLeft">Pions blancs à gauche</Text>
    <Text Name="LightRight">Pions blancs à droite</Text>
    <Text Name="LightTop">Pions blancs en haut</Text>
    <Text Name="Standard">Standard</Text>
    <Text Name="StandardInverted">Standard inversé</Text>
  </Group>


</Texts>

